{"cameraMode":{"drawMode":0,"name":"Shaded","section":"Shading Mode"},"sceneLighting":true,"audioPlay":false,"sceneViewState":{"m_AlwaysRefresh":false,"showFog":true,"showSkybox":true,"showFlares":true,"showImageEffects":true,"showParticleSystems":true,"showVisualEffectGraphs":true,"m_FxEnabled":true},"in2DMode":false,"pivot":{"x":0.23453445732593537,"y":0.9630627036094666,"z":-0.47294703125953677},"rotation":{"x":0.2780640125274658,"y":-0.5024418830871582,"z":0.1748739629983902,"w":0.7999722361564636},"size":0.14894749224185944,"orthographic":false}